{
  "Unit Tests": {
    "coverage": {
      "/Users/brad/turing/1608/enigma/lib/enigma.rb": [
        1,
        1,
        null,
        1,
        1,
        null,
        1,
        9,
        9,
        9,
        9,
        9,
        9,
        9,
        53,
        20,
        33,
        11,
        22,
        11,
        11,
        11,
        null,
        null,
        9,
        null,
        null,
        1,
        12347,
        12347,
        12347,
        12347,
        12347,
        12347,
        49388,
        null,
        12347,
        12347,
        12347,
        160503,
        49386,
        111117,
        37039,
        74078,
        37039,
        37039,
        37039,
        null,
        null,
        12347,
        null,
        null,
        1,
        1,
        1,
        1,
        null,
        null,
        1,
        12356,
        12356,
        12356,
        12356,
        12356,
        null,
        null,
        1,
        12356,
        12356,
        null,
        null,
        1,
        12356,
        12356,
        12356,
        12356,
        12356,
        12356,
        12356,
        12356,
        null,
        null,
        1,
        null,
        null,
        1,
        null,
        12346,
        12346,
        12346,
        null,
        null,
        null
      ],
      "/Users/brad/turing/1608/enigma/lib/offsets.rb": [
        1,
        1,
        1,
        null,
        1,
        1,
        null,
        null,
        1,
        12356,
        12351,
        12351,
        12351,
        12351,
        12351,
        12351,
        12351,
        12351,
        12351,
        5,
        0,
        5,
        0,
        null,
        5,
        5,
        5,
        5,
        null,
        null,
        null,
        null,
        1,
        12356,
        12356,
        12356,
        12356,
        12356,
        12356,
        null,
        null,
        null,
        null,
        null
      ],
      "/Users/brad/turing/1608/enigma/lib/key_generator.rb": [
        1,
        1,
        1,
        1,
        1,
        null,
        null,
        1,
        6,
        null,
        null,
        1,
        1,
        0,
        null,
        1,
        null,
        null,
        null,
        null
      ]
    },
    "timestamp": 1472682611
  }
}
